visivo/__init__.py
visivo/__main__.py
visivo/build.py
visivo/command_line.py
visivo/commands/__init__.py
visivo/commands/aggregate.py
visivo/commands/archive.py
visivo/commands/archive_phase.py
visivo/commands/authorize.py
visivo/commands/compile.py
visivo/commands/compile_phase.py
visivo/commands/create.py
visivo/commands/create_phase.py
visivo/commands/dbt.py
visivo/commands/dbt_phase.py
visivo/commands/deploy.py
visivo/commands/deploy_phase.py
visivo/commands/dist.py
visivo/commands/dist_phase.py
visivo/commands/init.py
visivo/commands/init_phase.py
visivo/commands/list.py
visivo/commands/list_phase.py
visivo/commands/migrate.py
visivo/commands/migrate_phase.py
visivo/commands/options.py
visivo/commands/parse_project_phase.py
visivo/commands/run.py
visivo/commands/run_phase.py
visivo/commands/serve.py
visivo/commands/serve_phase.py
visivo/commands/test.py
visivo/commands/test_phase.py
visivo/commands/utils.py
visivo/constants.py
visivo/copy_install_script.py
visivo/discovery/__init__.py
visivo/discovery/discover.py
visivo/generate_project_schema_json.py
visivo/jobs/__init__.py
visivo/jobs/dag_runner.py
visivo/jobs/filtered_runner.py
visivo/jobs/job.py
visivo/jobs/job_tracker.py
visivo/jobs/run_csv_script_job.py
visivo/jobs/run_input_job.py
visivo/jobs/run_insight_job.py
visivo/jobs/run_local_merge_job.py
visivo/jobs/run_source_connection_job.py
visivo/jobs/run_source_schema_job.py
visivo/jobs/run_sql_model_job.py
visivo/jobs/run_trace_job.py
visivo/jobs/utils.py
visivo/logger/__init__.py
visivo/logger/logger.py
visivo/logger/query_error_logger.py
visivo/logger/singleton.py
visivo/models/__init__.py
visivo/models/alert.py
visivo/models/base/base_model.py
visivo/models/base/context_string.py
visivo/models/base/env_var_string.py
visivo/models/base/eval_functions.py
visivo/models/base/eval_string.py
visivo/models/base/named_model.py
visivo/models/base/parent_model.py
visivo/models/base/pattern_string.py
visivo/models/base/project_dag.py
visivo-1.0.78.dist-info/METADATA
visivo-1.0.78.dist-info/WHEEL
visivo-1.0.78.dist-info/entry_points.txt
visivo-1.0.78.dist-info/RECORD
