Metadata-Version: 2.4
Name: visivo
Version: 1.0.78
Summary: Visivo CLI for BI and visualizations as code
Author: Visivo People
Requires-Python: >=3.10,<3.14
Classifier: Programming Language :: Python :: 3
Classifier: Programming Language :: Python :: 3.12
Classifier: Programming Language :: Python :: 3.13
Requires-Dist: Flask (>=2.2.3)
Requires-Dist: Jinja2 (>=3.1.2)
Requires-Dist: PyYAML (>=6.0)
Requires-Dist: aiofiles (>=24.1.0)
Requires-Dist: assertpy (>=1.1)
Requires-Dist: click (>=8.1.3)
Requires-Dist: clickhouse-sqlalchemy (>=0.3.0)
Requires-Dist: deepmerge (>=1.1.0)
Requires-Dist: duckdb-engine (>=0.14.0)
Requires-Dist: flask-socketio (>=5.5.1)
Requires-Dist: gitpython (>=3.1.32)
Requires-Dist: halo (>=0.0.31)
Requires-Dist: httpx (>=0.27.2)
Requires-Dist: jsonschema-rs (>=0.30.0)
Requires-Dist: matplotlib (>=3.7.1)
Requires-Dist: networkx (>=3.1)
Requires-Dist: numpy (>=1.26.0,<2.0.0)
Requires-Dist: polars (>=1.31.0,<2.0.0)
Requires-Dist: posthog (>=6.1.0,<7.0.0)
Requires-Dist: psycopg2-binary (>=2.9.5)
Requires-Dist: pyarrow (>=20.0.0)
Requires-Dist: pydantic (>=2.9.0)
Requires-Dist: pymysql (>=1.1.0)
Requires-Dist: python-dateutil (>=2.9.0.post0)
Requires-Dist: python-dotenv (>=1.0.0)
Requires-Dist: redshift-connector (>=2.1.8,<3.0.0)
Requires-Dist: requests (>=2.28.2)
Requires-Dist: ruamel-yaml (>=0.18.6)
Requires-Dist: snowflake-connector-python (>=3.7.0)
Requires-Dist: snowflake-sqlalchemy (>=1.6.1)
Requires-Dist: sql-formatter (>=0.6.2)
Requires-Dist: sqlalchemy (>=2.0.8)
Requires-Dist: sqlalchemy-bigquery (>=1.12.0)
Requires-Dist: sqlglot (>=27.0.0,<28.0.0)
Requires-Dist: tenacity (>=9.0.0)
Requires-Dist: termcolor (>=2.4.0)
Requires-Dist: tornado (>=6.3)
Requires-Dist: watchdog (>=6.0.0)
Project-URL: Documentation, https://docs.visivo.io/
